[
  {
    "title": "Sixty minutes (2024)",
    "poster": "https://encrypted-tbn0.gstatic.com/images?q=tbn:ANd9GcRwXnsu52wblH4N91dQ1Z6wjFEqW6w_CPTJg1hCB8XLWDqiWq8jgIDXZwb4&s=10",
    "group": "film dubbing",
    "url": "https://movieku.ukielaki8387.workers.dev/0:/Film%20dubbing/sixty%20minutes%20(2024).mp4",
    "type": "movie"
  },
  {
    "title": "Badland hunters (2024)",
    "poster": "https://encrypted-tbn0.gstatic.com/images?q=tbn:ANd9GcQGIyZVh_PpcCDwb0EyTs9BGVcOPLzaB77OIgfN9UtLlHufWKnhFs9K9RzF&s=10",
    "group": "film dubbing",
    "url": "https://movieku.ukielaki8387.workers.dev/0:/Film%20dubbing/Badland%20hunters%20(2024).mp4",
    "type": "movie"
  },
  {
    "title": "Beverly hills cop axel f (2024)",
    "poster": "https://encrypted-tbn0.gstatic.com/images?q=tbn:ANd9GcQzcrHe4kipp3LUFP1GWUKvsvoUy9jeovivUM_O_JEXTXg6B_smVyxtWd6C&s=10",
    "group": "film dubbing",
    "url": "https://movieku.ukielaki8387.workers.dev/0:/Film%20dubbing/Beverly%20hills%20cop%20%20Axel%20f%20%20(2024).mp4",
    "type": "movie"
  },
  {
    "title": "Spaceman (2024)",
    "poster": "https://encrypted-tbn0.gstatic.com/images?q=tbn:ANd9GcTE28W5p5haQMZNvcCP7FLmyHJeZszcxwjT4jPX-4uquTHGrq-wsCRobtaD&s=10",
    "group": "film dubbing",
    "url": "https://mutia1503.ukielaki88.workers.dev/0:/Album%20film%202/Movie%20dubbing/spaceman%20(2024).mp4",
    "type": "movie"
  },
  {
    "title": "Remember (2022)",
    "poster": "https://encrypted-tbn0.gstatic.com/images?q=tbn:ANd9GcS9neD0F004fY_nvhPcfGvYkBMM39ORB4eHoOGYJkc4UTZJzC4_URlfqSX4&s=10",
    "group": "film dubbing",
    "url": "https://movieku.ukielaki8387.workers.dev/0:/Movies%20dubbing/remember%202022.mp4",
    "type": "movie"
  },
  {
    "title": "Scary movie 4 (2006)",
    "poster": "https://encrypted-tbn0.gstatic.com/images?q=tbn:ANd9GcRxziByP_6NjsslNK0i7uiXKYnT-yJO40CcgJo4B5mGIXTrG7S4quY-RiJj&s=10",
    "group": "film dubbing",
    "url": "https://movieku.ukielaki8387.workers.dev/0:/Movies%20dubbing/Scary.Movie.4.2006.INDONESIA.1080p.HTSR.DSNP.WEB-DL.IRIT.AAC2.0.x264-bealive.mp4",
    "type": "movie"
  }
]
